yc_event_to_json/__init__.py
yc_event_to_json-0.2.dist-info/LICENSE
yc_event_to_json-0.2.dist-info/METADATA
yc_event_to_json-0.2.dist-info/WHEEL
yc_event_to_json-0.2.dist-info/top_level.txt
yc_event_to_json-0.2.dist-info/RECORD
