Metadata-Version: 2.1
Name: yc-event-to-json
Version: 0.2
Summary: Yandex Cloud event to json convertor.
Home-page: https://github.com/yababay/yc-event-to-json
Download-URL: https://github.com/yababay/yc-event-to-json/archive/v_01.tar.gz
Author: Михаил Беляков (Michael Belyakov)
Author-email: bigbelk@live.ru
License: MIT
Keywords: yc,yandex cloud function,json,post request
Platform: UNKNOWN
Classifier: Development Status :: 3 - Alpha
Classifier: Intended Audience :: Developers
Classifier: Topic :: Software Development :: Build Tools
Classifier: License :: OSI Approved :: MIT License
Classifier: Programming Language :: Python :: 3.9
License-File: LICENSE
